brunotest.py
core/__init__.py
core/compiler.py
core/imports.py
brunotest-0.1.1.1687008168.dist-info/METADATA
brunotest-0.1.1.1687008168.dist-info/WHEEL
brunotest-0.1.1.1687008168.dist-info/entry_points.txt
brunotest-0.1.1.1687008168.dist-info/top_level.txt
brunotest-0.1.1.1687008168.dist-info/RECORD
