Metadata-Version: 2.1
Name: brunotest
Version: 0.1.1.1687008168
Summary: CLI tool for robust autograder chaff testing
Home-page: https://github.com/BrownDeepLearning/brunotest
Author: Brown Deep Learning Staff
Author-email: cs1470htas@brown.edu
License: MIT
Classifier: Programming Language :: Python :: 3.10
Classifier: Operating System :: OS Independent
Requires-Python: >=3.10
Requires-Dist: click
Requires-Dist: gradescope-utils
Requires-Dist: setuptools
Requires-Dist: pytest
